mls_api/__init__.py
mls_api/assists.py
mls_api/auth.py
mls_api/fixtures.py
mls_api/historical.py
mls_api/latest_news.py
mls_api/offense.py
mls_api/players.py
mls_api/rtd.py
mls_api/six.py
mls_api/standings.py
mls_api/teams.py
mls_api/top_scorer.py
mls_api/version.py
mls_api-2.0.3.dist-info/LICENSE
mls_api-2.0.3.dist-info/METADATA
mls_api-2.0.3.dist-info/WHEEL
mls_api-2.0.3.dist-info/top_level.txt
mls_api-2.0.3.dist-info/RECORD
