Metadata-Version: 2.1
Name: mls-api
Version: 2.0.3
Summary: Python library for integrating with the MLS (Major League Soccer) API.
Home-page: https://horisystems.com/mls-api/
Author: Hori Systems Limited
Author-email: support@horisystems.com
License: MIT
Project-URL: Bug Tracker, https://github.com/horisystems/mlsapi-py-sdk/issues
Project-URL: Changes, https://github.com/horisystems/mlsapi-py-sdk/blob/main/CHANGELOG.md
Project-URL: Documentation, https://docs.mlssoccerapi.com/
Project-URL: Source Code, https://github.com/horisystems/mlsapi-py-sdk
Keywords: mls,mls api,mls_api,major league soccer,hori,horisystems,hori systems
Classifier: Development Status :: 5 - Production/Stable
Classifier: Intended Audience :: Developers
Classifier: License :: OSI Approved :: MIT License
Classifier: Operating System :: OS Independent
Classifier: Programming Language :: Python
Classifier: Programming Language :: Python :: 2
Classifier: Programming Language :: Python :: 2.7
Classifier: Programming Language :: Python :: 3
Classifier: Programming Language :: Python :: 3.4
Classifier: Programming Language :: Python :: 3.5
Classifier: Programming Language :: Python :: 3.6
Classifier: Programming Language :: Python :: 3.7
Classifier: Programming Language :: Python :: 3.8
Classifier: Programming Language :: Python :: 3.9
Classifier: Programming Language :: Python :: 3.10
Classifier: Programming Language :: Python :: Implementation :: PyPy
Classifier: Topic :: Software Development :: Libraries :: Python Modules
Requires-Python: >=2.7, !=3.0.*, !=3.1.*, !=3.2.*, !=3.3.*
License-File: LICENSE
Requires-Dist: requests
